mcetl/__init__.py
mcetl/data_source.py
mcetl/excel_writer.py
mcetl/file_organizer.py
mcetl/functions.py
mcetl/main_gui.py
mcetl/plot_utils.py
mcetl/raw_data.py
mcetl/utils.py
mcetl/fitting/__init__.py
mcetl/fitting/fitting_gui.py
mcetl/fitting/fitting_utils.py
mcetl/fitting/models.py
mcetl/fitting/peak_fitting.py
mcetl/plotting/__init__.py
mcetl/plotting/plotting_gui.py
mcetl-0.4.2.dist-info/LICENSE.txt
mcetl-0.4.2.dist-info/METADATA
mcetl-0.4.2.dist-info/WHEEL
mcetl-0.4.2.dist-info/top_level.txt
mcetl-0.4.2.dist-info/RECORD
