Metadata-Version: 2.1
Name: mcetl
Version: 0.4.2
Summary: A small-scale Extract-Transform-Load framework focused on materials characterization.
Home-page: https://github.com/derb12/mcetl
Author: Donald Erb
Author-email: donnie.erb@gmail.com
License: BSD 3-clause
Keywords: materials characterization,materials science,materials engineering
Platform: UNKNOWN
Classifier: Development Status :: 4 - Beta
Classifier: Intended Audience :: Science/Research
Classifier: License :: OSI Approved :: BSD License
Classifier: Natural Language :: English
Classifier: Operating System :: OS Independent
Classifier: Programming Language :: Python :: 3
Classifier: Programming Language :: Python :: 3.7
Classifier: Programming Language :: Python :: 3.8
Classifier: Programming Language :: Python :: 3.9
Classifier: Topic :: Scientific/Engineering :: Chemistry
Classifier: Topic :: Scientific/Engineering :: Information Analysis
Classifier: Topic :: Scientific/Engineering :: Physics
Classifier: Topic :: Scientific/Engineering :: Visualization
Requires-Python: >=3.7
Requires-Dist: asteval
Requires-Dist: lmfit (>=1.0)
Requires-Dist: matplotlib (>=3.1)
Requires-Dist: numpy (>=1.8)
Requires-Dist: openpyxl (>=2.4)
Requires-Dist: pandas (>=0.25)
Requires-Dist: pysimplegui (>=4.29)
Requires-Dist: scipy
